rrmscorer/__init__.py
rrmscorer/__main__.py
rrmscorer/rrm_rna_functions.py
rrmscorer/alignment_data/RNAs_aligned_cluster_0_nt_full_refined.fasta
rrmscorer/alignment_data/RRM_master_interaction_info_with_nt_unbiased_cluster_0.json
rrmscorer/alignment_data/cluster_0_contacts_values_for_confidence.json
rrmscorer/alignment_data/leave-one-out_negative_scores_avg_perc_20.txt
rrmscorer/alignment_data/leave-one-out_positive_scores_avg_perc_20.txt
rrmscorer/alignment_data/leave_one_out_neg_confidence_scores.txt
rrmscorer/alignment_data/leave_one_out_pos_confidence_scores.txt
rrmscorer/alignment_data/neighbours_rna_cluster_0.json
rrmscorer/alignment_data/rrm_bound.hmm
rrmscorer/alignment_data/rrm_bound.hmm.h3f
rrmscorer/alignment_data/rrm_bound.hmm.h3i
rrmscorer/alignment_data/rrm_bound.hmm.h3m
rrmscorer/alignment_data/rrm_bound.hmm.h3p
rrmscorer/alignment_data/rrm_bound_domains_aligned_processed_squeezed.fasta
rrmscorer/alignment_data/sxl_seqs_phage_display_A1_aligned.fasta
rrmscorer/alignment_data/precalculated_scores/122_5.pkl
rrmscorer/alignment_data/precalculated_scores/122_6.pkl
rrmscorer/alignment_data/precalculated_scores/124_5.pkl
rrmscorer/alignment_data/precalculated_scores/124_6.pkl
rrmscorer/alignment_data/precalculated_scores/126_6.pkl
rrmscorer/alignment_data/precalculated_scores/135_3.pkl
rrmscorer/alignment_data/precalculated_scores/137_3.pkl
rrmscorer/alignment_data/precalculated_scores/137_5.pkl
rrmscorer/alignment_data/precalculated_scores/139_4.pkl
rrmscorer/alignment_data/precalculated_scores/139_5.pkl
rrmscorer/alignment_data/precalculated_scores/141_5.pkl
rrmscorer/alignment_data/precalculated_scores/166_2.pkl
rrmscorer/alignment_data/precalculated_scores/169_2.pkl
rrmscorer/alignment_data/precalculated_scores/169_3.pkl
rrmscorer/alignment_data/precalculated_scores/171_3.pkl
rrmscorer/alignment_data/precalculated_scores/171_4.pkl
rrmscorer/alignment_data/precalculated_scores/173_4.pkl
rrmscorer/alignment_data/precalculated_scores/173_5.pkl
rrmscorer-1.0.11.dist-info/licenses/LICENSE
rrmscorer-1.0.11.dist-info/METADATA
rrmscorer-1.0.11.dist-info/WHEEL
rrmscorer-1.0.11.dist-info/entry_points.txt
rrmscorer-1.0.11.dist-info/top_level.txt
rrmscorer-1.0.11.dist-info/RECORD
