Metadata-Version: 2.4
Name: rrmscorer
Version: 1.0.11
Summary: RRM-RNA score predictor
Home-page: https://bio2byte.be/rrmscorer
Author: Joel Roca-Martinez (ORCID: 0000-0002-4313-3845), Wim Vranken (ORCID: 0000-0001-7470-4324)
Author-email: bio2byte@vub.be, wim.vranken@vub.be, joel.roca@ucl.ac.uk
Maintainer: Joel Roca-Martinez (ORCID: 0000-0002-4313-3845), Wim Vranken (ORCID: 0000-0001-7470-4324), Adrián Díaz (ORCID: 0000-0003-0165-1318)
Maintainer-email: bio2byte@vub.be, wim.vranken@vub.be, adrian.diaz@vub.be
License: MIT
Project-URL: Documentation, https://bitbucket.org/bio2byte/rrmscorer/raw/master/readme.md
Project-URL: Source, https://bitbucket.org/bio2byte/rrmscorer/
Project-URL: Say Thanks!, https://bio2byte.be/info/
Keywords: proteins RRM RNA predictor sequence bio2byte
Platform: Linux
Platform: MacOS
Classifier: Natural Language :: English
Classifier: Programming Language :: Python :: 3.9
Classifier: Programming Language :: Python :: 3.10
Classifier: Programming Language :: Python :: 3.11
Classifier: Programming Language :: Python :: 3.12
Classifier: Programming Language :: Python :: 3.13
Classifier: License :: OSI Approved :: MIT License
Classifier: Operating System :: MacOS
Classifier: Operating System :: POSIX :: Linux
Classifier: Topic :: Scientific/Engineering :: Bio-Informatics
Classifier: Topic :: Scientific/Engineering :: Chemistry
Classifier: Intended Audience :: Science/Research
Classifier: Intended Audience :: Education
Classifier: Development Status :: 5 - Production/Stable
Requires-Python: >=3.9
License-File: LICENSE
Requires-Dist: biopython
Requires-Dist: numpy
Requires-Dist: pandas
Requires-Dist: requests
Requires-Dist: scikit-learn
Requires-Dist: matplotlib
Requires-Dist: logomaker
Requires-Dist: seaborn
Provides-Extra: dev
Requires-Dist: unittest; extra == "dev"
Provides-Extra: docs
Dynamic: author
Dynamic: author-email
Dynamic: classifier
Dynamic: description
Dynamic: description-content-type
Dynamic: home-page
Dynamic: keywords
Dynamic: license
Dynamic: license-file
Dynamic: maintainer
Dynamic: maintainer-email
Dynamic: platform
Dynamic: project-url
Dynamic: provides-extra
Dynamic: requires-dist
Dynamic: requires-python
Dynamic: summary
